inventree_serial_number_tags-0.1.0.dist-info/licenses/LICENSE
serial_number_tags/__init__.py
serial_number_tags/core.py
inventree_serial_number_tags-0.1.0.dist-info/METADATA
inventree_serial_number_tags-0.1.0.dist-info/WHEEL
inventree_serial_number_tags-0.1.0.dist-info/entry_points.txt
inventree_serial_number_tags-0.1.0.dist-info/top_level.txt
inventree_serial_number_tags-0.1.0.dist-info/RECORD
