Metadata-Version: 2.4
Name: inventree-serial-number-tags
Version: 0.1.0
Summary: Enforce unique serial numbers based on part tags
Home-page: https://github.com/SchrodingersGat/inventree-serial-tags
Author: Oliver Walters
Author-email: oliver.henry.walters@gmail.com
License: MIT
Requires-Python: >=3.9
License-File: LICENSE
Dynamic: author
Dynamic: author-email
Dynamic: description
Dynamic: description-content-type
Dynamic: home-page
Dynamic: license
Dynamic: license-file
Dynamic: requires-python
Dynamic: summary
